dmttsgen/__init__.py
dmttsgen/generator.py
dmttsgen/generators/__init__.py
dmttsgen/generators/basic_template_generator.py
dmttsgen/generators/entity_generator.py
dmttsgen/generators/package_descriptor_generator.py
dmttsgen/generators/package_info_generator.py
dmttsgen/generators/runtime_generator.py
dmttsgen/templates/package.json.jinja
dmttsgen/templates/publish.sh
dmttsgen/templates/tsconfig.json
dmttsgen/templates/src/entity-minimal.ts.jinja
dmttsgen/templates/src/package_descriptor.ts.jinja
dmttsgen/templates/src/poto.ts.jinja
dmttsgen-0.3.0.dist-info/LICENSE
dmttsgen-0.3.0.dist-info/METADATA
dmttsgen-0.3.0.dist-info/WHEEL
dmttsgen-0.3.0.dist-info/top_level.txt
dmttsgen-0.3.0.dist-info/RECORD
