Metadata-Version: 2.1
Name: dmttsgen
Version: 0.3.0
Summary: Typescript generator for SIMOS based DMT models
Home-page: UNKNOWN
Author: SINTEF Ocean
License: UNKNOWN
Platform: UNKNOWN
Classifier: Programming Language :: Python :: 3
Classifier: License :: OSI Approved :: MIT License
Classifier: Operating System :: OS Independent
Requires-Python: >=3.8
Requires-Dist: jinja2 (==3.0.2)
Requires-Dist: dmtgen (==0.3.0)
Requires-Dist: docopt (==0.6.2)
